agentify_lara/__init__.py
agentify_lara/agents.py
agentify_lara/chat_models.py
agentify_lara/models.py
agentify_lara/task.py
agentify_lara/tools.py
agentify_lara/prebulit/__init__.py
agentify_lara/prebulit/agents.py
agentify_lara/prebulit/apps.py
agentify_lara-0.3.dist-info/licenses/LICENSE
agentify_lara-0.3.dist-info/METADATA
agentify_lara-0.3.dist-info/WHEEL
agentify_lara-0.3.dist-info/top_level.txt
agentify_lara-0.3.dist-info/RECORD
